{"blogs_c___baseproblem.md":"BpN6t8nN","blogs_c___gdal.md":"BhfbTZGb","blogs_c___vscode.md":"CUosgu1d","blogs_gis_bindmap.md":"y6wMrDKG","blogs_gis_cesium_cesiumforue.md":"TikKallu","blogs_gis_cesium_normalapi.md":"B2dtF4o4","blogs_gis_interview.md":"BF2wfiRn","blogs_gis_mapbox_drawonline.md":"C_LoLG1O","blogs_gis_mapbox_gradient.md":"CW6oZ80_","blogs_gis_mapbox_mapbox-three.md":"DF_RaOlC","blogs_gis_mapbox_mapbox1-1.md":"CSW1ZcKd","blogs_gis_mapbox_mapbox1-10.md":"BdM8TG4F","blogs_gis_mapbox_mapbox1-2.md":"T5DJHDay","blogs_gis_mapbox_mapbox1-3.md":"kixUaMMG","blogs_gis_mapbox_mapbox1-4.md":"Dl7mZWmH","blogs_gis_mapbox_mapbox1-5.md":"PYyT65F5","blogs_gis_mapbox_mapbox1-6.md":"C0Q4M3fE","blogs_gis_mapbox_mapbox1-7.md":"Cq7fz-4Q","blogs_gis_mapbox_mapbox1-8.md":"DCFKZxBP","blogs_gis_mapbox_mapbox1-9.md":"Tes918kr","blogs_gis_mapbox_mapbox2-1.md":"DI4L9b1R","blogs_gis_mapbox_mapbox2-2 copy.md":"CXRGZB5O","blogs_gis_mapbox_mapbox2-2.md":"DlmuL8MG","blogs_gis_mapbox_mapbox2-3.md":"DTyTzqAW","blogs_gis_mapbox_mapbox2-4.md":"CDUja3-0","blogs_gis_mapbox_mapbox3-1.md":"RtahtQex","blogs_gis_mapbox_mapbox3-2.md":"c06win-0","blogs_gis_mapbox_performance.md":"Cw0YTMti","blogs_gis_mapbox_sourcecode1.md":"p5drIymz","blogs_gis_performance.md":"BgVfh655","blogs_gis_problemset.md":"B08HC3Ib","blogs_gis_split.md":"B9V_oIY7","blogs_gis_three_calcnormal.md":"BJY3x00p","blogs_gis_three_custommaterial.md":"CNPgiCCT","blogs_gis_three_fly.md":"BJwm7Enf","blogs_gis_three_matrix.md":"DK63WMXj","blogs_gis_three_problemset.md":"Moff7K0C","blogs_gis_three_radar.md":"eX8BDdtz","blogs_gis_three_wall.md":"Cn5YQNmD","blogs_gis_webgl_basefunction.md":"y7BnB_Nh","blogs_gis_webgl_basefunction2.md":"Cjb_aKkK","blogs_gis_webgl_normalerror.md":"B4sPOL5T","blogs_gis_webgl_normalfunction.md":"BSa9OqTW","blogs_gis_webgl_the book of shaders1.md":"DQWno20G","blogs_gis_webgl_the book of shaders2.md":"Ik5l3XpE","blogs_gis_webgl_webgl2.md":"BFaXNkp5","blogs_gis_webgpu_leranwebgpu.md":"-oO5Wnkc","blogs_life_conclusion_2021.md":"BLWp8oi0","blogs_life_conclusion_2022.md":"DHe2RnXO","blogs_life_conclusion_2023.md":"BfKsfwjv","blogs_server_base.md":"D2EHMX_K","blogs_ue_3dtile.md":"Hz88_-F1","blogs_ue_base.md":"Ca8-or-m","blogs_ue_cesiumforue.md":"Cmmg-ESL","blogs_ue_readwritejson.md":"DH9FGh0X","blogs_web_github_githubactions.md":"r2KcItSn","blogs_web_github_githubactions2.md":"DPV2nDyN","blogs_web_github_githubactions3.md":"ncY5fhlm","blogs_web_github_problemset.md":"BkwtGj5s","blogs_web_github_sshkey.md":"2cngVb1p","blogs_web_interview.md":"DDchQ1NV","blogs_web_node_cluster.md":"k9ObziH_","blogs_web_node_mongodb.md":"BLkm9fJA","blogs_web_node_problemset.md":"_tGavsYb","blogs_web_node_problemset2.md":"qgTgI0T3","blogs_web_node_readwrite.md":"C4v9mru7","blogs_web_normalcommand.md":"r40ffQsy","blogs_web_normalfunction.md":"vE4iCtQP","blogs_web_other_cmd.md":"DzpGABj9","blogs_web_other_exifreader.md":"UfbCIrM3","blogs_web_other_md.md":"zrDlgGZv","blogs_web_other_painter.md":"D5BQqKLv","blogs_web_other_panoramic.md":"D0SVOrHW","blogs_web_other_vscode.md":"C12SYQGW","blogs_web_problemset.md":"BuUnK7eW","blogs_web_problemset2.md":"D8NZOSrV","blogs_web_project_ruler.md":"CoOOkBfV","blogs_web_vitepress_learn.md":"CQEpwvKu","blogs_web_vue_vitesse.md":"D6J7ZZKQ","blogs_web_vuepress_advice.md":"V44wXw8g","blogs_web_vuepress_leancloud.md":"qil2cA1W","blogs_web_vuepress_problemset.md":"D0-k6KhK","category.md":"CNmYuL2K","docs_index.md":"UMO8TFSd","docs_ruler_getting-started.md":"COYmBCD3","docs_ruler_params.md":"B8kG4nt4","docs_vitepresstreehole_doc.md":"DPIfJO_N","docs_vitepresstreehole_getting-started.md":"Bo0noGEq","docs_vitepresstreehole_giscus.md":"DIv9PuX7","docs_vitepresstreehole_memo.md":"CaX_Gs5n","docs_vitepresstreehole_params.md":"DyCiEfl0","docs_vitepresstreehole_tag-category.md":"BYr8SfZ2","docs_vitepresstreehole_umami.md":"j4pOcfbc","index.md":"BDTJZCB2","me.md":"CQWV-XcO","memo.md":"D8HZceIb","messageboard.md":"DmzFnhuC","project.md":"BaIofb5O","tag.md":"NpTlS11-","timeline.md":"Do6ERl-c"}
